ari_client/__init__.py
ari_client/ari_client.py
ari_client/controller.py
ari_client/py.typed
ari_client/models/bridge.py
ari_client/models/channels.py
ari_client/models/events.py
ari_client-0.2.6.dist-info/licenses/LICENSE
ari_client-0.2.6.dist-info/METADATA
ari_client-0.2.6.dist-info/WHEEL
ari_client-0.2.6.dist-info/top_level.txt
ari_client-0.2.6.dist-info/RECORD
