Metadata-Version: 2.4
Name: ari_client
Version: 0.2.6
Summary: asyncio native asterisk client for python
Requires-Python: >=3.10
License-File: LICENSE
Requires-Dist: httpx>=0.28.1
Requires-Dist: pydantic>=2.12.5
Requires-Dist: websockets>=15.0.1
Provides-Extra: testing
Requires-Dist: pytest>=8.4.2; extra == "testing"
Requires-Dist: pytest-asyncio>=0.21.0; extra == "testing"
Requires-Dist: pytest-cov>=4.1.0; extra == "testing"
Dynamic: license-file
